nina_advanced_mcp/__init__.py
nina_advanced_mcp/nina_help.json
nina_advanced_mcp/nina_help_en.json
nina_advanced_mcp-0.1.0.dist-info/METADATA
nina_advanced_mcp-0.1.0.dist-info/WHEEL
nina_advanced_mcp-0.1.0.dist-info/top_level.txt
nina_advanced_mcp-0.1.0.dist-info/RECORD
